AUTHORS.rst
CONTRIBUTING.rst
HISTORY.rst
LICENSE
MANIFEST.in
README.rst
recursive_dict.py
setup.cfg
setup.py
docs/Makefile
docs/authors.rst
docs/conf.py
docs/contributing.rst
docs/history.rst
docs/index.rst
docs/installation.rst
docs/make.bat
docs/readme.rst
docs/usage.rst
recursive_dict.egg-info/PKG-INFO
recursive_dict.egg-info/SOURCES.txt
recursive_dict.egg-info/dependency_links.txt
recursive_dict.egg-info/not-zip-safe
recursive_dict.egg-info/top_level.txt
tests/__init__.py
tests/test_recursive_dict.py