Metadata-Version: 1.1
Name: recursive-dict
Version: 0.2.0
Summary: A dict subclass that can lookup several layers deep.
Home-page: https://github.com/ryananguiano/recursive_dict
Author: Ryan Anguiano
Author-email: ryan.anguiano@gmail.com
License: ISCL
Keywords: recursive_dict
Platform: UNKNOWN
Classifier: Development Status :: 2 - Pre-Alpha
Classifier: Intended Audience :: Developers
Classifier: License :: OSI Approved :: ISC License (ISCL)
Classifier: Natural Language :: English
Classifier: Programming Language :: Python :: 2
Classifier: Programming Language :: Python :: 2.6
Classifier: Programming Language :: Python :: 2.7
Classifier: Programming Language :: Python :: 3
Classifier: Programming Language :: Python :: 3.3
Classifier: Programming Language :: Python :: 3.4
